{"changelog.md":"Bgk21soM","donate.md":"ZVN839ST","guide_demo.md":"APODhpRu","guide_development.md":"Bv5R3S6k","guide_distribution.md":"YdTO3-to","guide_faq.md":"B_J1ryrf","guide_formats.md":"CXfE1o_a","guide_iframe.md":"BiGWSnQe","guide_index.md":"BtZDQYg0","guide_overview.md":"CML3Kk3Z","guide_quickstart-react.md":"96QtA-ST","guide_quickstart-vue2.md":"D7uz9dlP","guide_quickstart-vue3.md":"odnQF2DM","guide_quickstart-web.md":"BDrcaXcD","guide_quickstart.md":"DflhYS4I","guide_usage.md":"Ca3EFuHe","index.md":"CZpsOegW"}
